examples/README.md
examples/__init__.py
examples/basic.py
examples/example_decorator.py
examples/example_openai_sdk.py
examples/example_perplexity_sdk.py
examples/example_streaming_perplexity_sdk.py
examples/example_tracing.py
examples/getting_started.py
examples/streaming.py
examples/trace_visualization.py
revenium_middleware_perplexity/__init__.py
revenium_middleware_perplexity/middleware.py
revenium_middleware_perplexity/perplexity_sdk.py
revenium_middleware_perplexity/provider.py
revenium_middleware_perplexity/trace_fields.py
revenium_middleware_perplexity-0.1.0.dist-info/licenses/LICENSE
revenium_middleware_perplexity-0.1.0.dist-info/METADATA
revenium_middleware_perplexity-0.1.0.dist-info/WHEEL
revenium_middleware_perplexity-0.1.0.dist-info/top_level.txt
revenium_middleware_perplexity-0.1.0.dist-info/RECORD
