Metadata-Version: 2.4
Name: revenium-middleware-perplexity
Version: 0.1.0
Summary: A Python library that meters Perplexity AI usage to Revenium.
Author-email: Revenium <info@revenium.io>
License: MIT
Project-URL: Homepage, https://github.com/revenium/revenium-middleware-perplexity-python
Project-URL: Bug Tracker, https://github.com/revenium/revenium-middleware-perplexity-python/issues
Project-URL: Documentation, https://github.com/revenium/revenium-middleware-perplexity-python/blob/main/README.md
Keywords: perplexity,middleware,logging,token-usage,metering,revenium,ai,llm
Classifier: Development Status :: 4 - Beta
Classifier: Programming Language :: Python :: 3
Classifier: Programming Language :: Python :: 3.8
Classifier: Programming Language :: Python :: 3.9
Classifier: Programming Language :: Python :: 3.10
Classifier: Programming Language :: Python :: 3.11
Classifier: Programming Language :: Python :: 3.12
Classifier: License :: OSI Approved :: MIT License
Classifier: Operating System :: OS Independent
Classifier: Intended Audience :: Developers
Classifier: Topic :: Software Development :: Libraries :: Python Modules
Requires-Python: >=3.8
License-File: LICENSE
Requires-Dist: wrapt
Requires-Dist: revenium_middleware>=0.3.5
Requires-Dist: python-dotenv>=0.19.0
Provides-Extra: openai
Requires-Dist: openai>=1.0.0; extra == "openai"
Provides-Extra: perplexity
Requires-Dist: perplexityai>=0.1.0; extra == "perplexity"
Provides-Extra: all
Requires-Dist: openai>=1.0.0; extra == "all"
Requires-Dist: perplexityai>=0.1.0; extra == "all"
Provides-Extra: dev
Requires-Dist: pytest>=7.0.0; extra == "dev"
Requires-Dist: pytest-cov; extra == "dev"
Requires-Dist: flake8; extra == "dev"
Requires-Dist: black; extra == "dev"
Requires-Dist: mypy; extra == "dev"
Requires-Dist: openai-responses>=0.12.0; extra == "dev"
Requires-Dist: freezegun; extra == "dev"
Requires-Dist: openai>=1.0.0; extra == "dev"
Requires-Dist: perplexityai>=0.1.0; extra == "dev"
Dynamic: license-file
